cpyvpn/__init__.py
cpyvpn/__version__.py
cpyvpn/appdirs.py
cpyvpn/auth.py
cpyvpn/cfg.py
cpyvpn/client.py
cpyvpn/crt.py
cpyvpn/cui.py
cpyvpn/ma.py
cpyvpn/rsa.py
cpyvpn/snx.py
cpyvpn/ssl_ctx.py
cpyvpn/trutils.py
cpyvpn/utils.py
cpyvpn/vna.py
cpyvpn-1.6.2.dist-info/LICENSE
cpyvpn-1.6.2.dist-info/LICENSE-GPLv3
cpyvpn-1.6.2.dist-info/METADATA
cpyvpn-1.6.2.dist-info/WHEEL
cpyvpn-1.6.2.dist-info/entry_points.txt
cpyvpn-1.6.2.dist-info/top_level.txt
cpyvpn-1.6.2.dist-info/zip-safe
cpyvpn-1.6.2.dist-info/RECORD
