Metadata-Version: 2.1
Name: cpyvpn
Version: 1.6.2
Summary: Check Point VPN client written in Python.
Home-page: https://gitlab.com/cpvpn/cpyvpn
Author: Nikolay A. Krylov
Author-email: krylovna@gmail.com
License: GPL3
Project-URL: PyPI, https://pypi.org/project/cpyvpn
Project-URL: Source, https://gitlab.com/cpvpn/cpyvpn
Project-URL: Tracker, https://gitlab.com/cpvpn/cpyvpn/issues
Keywords: CheckPoint vpn snx
Classifier: Programming Language :: Python
Classifier: Programming Language :: Python :: 3
Classifier: Programming Language :: Python :: 3 :: Only
Classifier: Topic :: System :: Networking
Classifier: Operating System :: POSIX
Classifier: Operating System :: Unix
Classifier: License :: OSI Approved :: GNU General Public License v3 or later (GPLv3+)
Classifier: Development Status :: 4 - Beta
Classifier: Intended Audience :: End Users/Desktop
Classifier: Intended Audience :: Developers
License-File: LICENSE
License-File: LICENSE-GPLv3
